rtx/__init__.py
rtx/data_util.py
rtx/efficient_net.py
rtx/rtx1.py
rtx/rtx2.py
rtx_torch-0.1.3.dist-info/LICENSE
rtx_torch-0.1.3.dist-info/WHEEL
rtx_torch-0.1.3.dist-info/METADATA
rtx_torch-0.1.3.dist-info/RECORD
