Metadata-Version: 2.1
Name: rtx-torch
Version: 0.1.3
Summary: rtx - Pytorch
Home-page: https://github.com/kyegomez/rt-x
License: MIT
Keywords: artificial intelligence,deep learning,optimizers,Prompt Engineering
Author: Kye Gomez
Author-email: kye@apac.ai
Requires-Python: >=3.9,<3.12
Classifier: Development Status :: 4 - Beta
Classifier: Intended Audience :: Developers
Classifier: License :: OSI Approved :: MIT License
Classifier: Programming Language :: Python :: 3
Classifier: Programming Language :: Python :: 3.9
Classifier: Programming Language :: Python :: 3.10
Classifier: Programming Language :: Python :: 3.11
Classifier: Programming Language :: Python :: 3.6
Classifier: Topic :: Scientific/Engineering :: Artificial Intelligence
Requires-Dist: classifier-free-guidance-pytorch (==0.5.2)
Requires-Dist: efficientnet_pytorch (==0.7.1)
Requires-Dist: einops (==0.7.0)
Requires-Dist: lz4 (>=4.3.2,<5.0.0)
Requires-Dist: olefile (>=0.47,<0.48)
Requires-Dist: tensorboard (>=2.15.1,<3.0.0)
Requires-Dist: tensorboardx (>=2.6.2.2,<3.0.0.0)
Requires-Dist: torch
Requires-Dist: torch-tb-profiler (>=0.4.3,<0.5.0)
Requires-Dist: torchvision (>=0.16.2,<0.17.0)
Requires-Dist: zetascale (==1.2.5)
Project-URL: Documentation, https://github.com/kyegomez/rt-x
Project-URL: Repository, https://github.com/kyegomez/rtx
